django_fastadmin/__init__.py
django_fastadmin/admin.py
django_fastadmin/apps.py
django_fastadmin/list_filters.py
django_fastadmin/models.py
django_fastadmin/settings.py
django_fastadmin/tests.py
django_fastadmin/urls.py
django_fastadmin/utils.py
django_fastadmin/views.py
django_fastadmin/widgets.py
django_fastadmin/locale/zh_Hans/LC_MESSAGES/django.mo
django_fastadmin/locale/zh_Hans/LC_MESSAGES/django.po
django_fastadmin/migrations/__init__.py
django_fastadmin/static/fastadmin/django-admin.utils.js
django_fastadmin/static/fastadmin/admins/editable-password-field/editable-password-field.css
django_fastadmin/static/fastadmin/admins/editable-password-field/editable-password-field.js
django_fastadmin/static/fastadmin/admins/hide-show-field/hide-show-field.css
django_fastadmin/static/fastadmin/admins/hide-show-field/hide-show-field.js
django_fastadmin/static/fastadmin/admins/hide-show-fields-on-value-admin/jquery.set-form-class-on-field-value-changes.js
django_fastadmin/static/fastadmin/admins/inline-boolean-fields-allow-only-one-checked-mixin/ibfaoocm.js
django_fastadmin/static/fastadmin/admins/inline-editing-hide-original-mixin/inline-editing-hide-original-mixin.css
django_fastadmin/static/fastadmin/admins/reset-to-random-password-field/reset-to-random-password-field.css
django_fastadmin/static/fastadmin/admins/reset-to-random-password-field/reset-to-random-password-field.js
django_fastadmin/static/fastadmin/admins/text-field-auto-height-mixin/text-field-auto-height-mixin.js
django_fastadmin/static/fastadmin/widgets/ace-widget/ace-widget.css
django_fastadmin/static/fastadmin/widgets/ace-widget/ace-widget.js
django_fastadmin/static/fastadmin/widgets/categoried-select-multiple/categoried-select-multiple.css
django_fastadmin/static/fastadmin/widgets/categoried-select-multiple/categoried-select-multiple.js
django_fastadmin/static/fastadmin/widgets/title-to-code/title-to-code.js
django_fastadmin/templates/admin/change_form_object_tools.html
django_fastadmin-0.7.6.dist-info/licenses/LICENSE
django_fastadmin-0.7.6.dist-info/METADATA
django_fastadmin-0.7.6.dist-info/WHEEL
django_fastadmin-0.7.6.dist-info/top_level.txt
django_fastadmin-0.7.6.dist-info/RECORD
