Metadata-Version: 2.4
Name: django-fastadmin
Version: 0.7.6
Summary: django admin extensions.
Author: rRR0VrFP
Maintainer: rRR0VrFP
License: MIT
Keywords: django admin extentions
Classifier: Development Status :: 5 - Production/Stable
Classifier: Intended Audience :: Developers
Classifier: Topic :: Software Development :: Libraries :: Python Modules
Classifier: License :: OSI Approved :: MIT License
Classifier: Programming Language :: Python :: 3
Classifier: Programming Language :: Python :: 3 :: Only
License-File: LICENSE
Requires-Dist: Django
Requires-Dist: django-apiview>=0.9.27
Requires-Dist: django-middleware-global-request>=0.2.0
Requires-Dist: django-static-ace-builds>=1.4.12.0
Requires-Dist: django-static-fontawesome>=5.14.0.0
Requires-Dist: django-static-jquery3>=5.1.0
Requires-Dist: fastutils
Requires-Dist: magic-import>=0.1.3
Dynamic: author
Dynamic: classifier
Dynamic: description
Dynamic: description-content-type
Dynamic: keywords
Dynamic: license
Dynamic: license-file
Dynamic: maintainer
Dynamic: requires-dist
Dynamic: summary
